ericsda_calculator.py
ericsda_calculator-0.1.0.dist-info/METADATA
ericsda_calculator-0.1.0.dist-info/WHEEL
ericsda_calculator-0.1.0.dist-info/RECORD
