Metadata-Version: 2.1
Name: ericsda-calculator
Version: 0.1.0
Summary: Simple Calculator Package
Author: ericsalesdeandrade
Author-email: sdaeric19@gmail.com
Requires-Python: >=3.10,<4.0
Classifier: Programming Language :: Python :: 3
Classifier: Programming Language :: Python :: 3.10
Classifier: Programming Language :: Python :: 3.11
Requires-Dist: requests (>=2.31.0,<3.0.0)
